aule/__init__.py
aule/comfy_node.py
aule/patching.py
aule/triton_flash.py
aule/triton_flash_amd.py
aule/vulkan.py
aule/lib/aule.dll
aule/lib/libaule.so
aule_attention-0.5.0.dist-info/METADATA
aule_attention-0.5.0.dist-info/WHEEL
aule_attention-0.5.0.dist-info/top_level.txt
aule_attention-0.5.0.dist-info/RECORD
