Metadata-Version: 2.4
Name: aule-attention
Version: 0.5.0
Summary: FlashAttention that just works. No compilation. Any GPU. AMD ROCm, NVIDIA CUDA, Intel, Apple via Vulkan.
Author-email: Aule Technologies <contact@aule.dev>
License: MIT
Project-URL: Homepage, https://github.com/xenn0010/Aule-Attention
Project-URL: Documentation, https://github.com/xenn0010/Aule-Attention#readme
Project-URL: Repository, https://github.com/xenn0010/Aule-Attention
Project-URL: Issues, https://github.com/xenn0010/Aule-Attention/issues
Keywords: attention,flashattention,flash-attention,transformer,deep-learning,gpu,amd,rocm,nvidia,cuda,intel,vulkan,triton,llm,gqa,mqa
Classifier: Development Status :: 4 - Beta
Classifier: Intended Audience :: Developers
Classifier: Intended Audience :: Science/Research
Classifier: License :: OSI Approved :: MIT License
Classifier: Operating System :: OS Independent
Classifier: Programming Language :: Python :: 3
Classifier: Programming Language :: Python :: 3.8
Classifier: Programming Language :: Python :: 3.9
Classifier: Programming Language :: Python :: 3.10
Classifier: Programming Language :: Python :: 3.11
Classifier: Programming Language :: Python :: 3.12
Classifier: Topic :: Scientific/Engineering :: Artificial Intelligence
Requires-Python: >=3.8
Requires-Dist: numpy<3.0,>=1.19.0
Provides-Extra: triton
Requires-Dist: triton<4.0,>=2.0.0; extra == "triton"
Provides-Extra: torch
Requires-Dist: torch<3.0,>=2.0.0; extra == "torch"
Provides-Extra: full
Requires-Dist: torch<3.0,>=2.0.0; extra == "full"
Requires-Dist: triton<4.0,>=2.0.0; extra == "full"
Provides-Extra: dev
Requires-Dist: pytest<9.0,>=6.0; extra == "dev"
Requires-Dist: pytest-benchmark<5.0,>=4.0; extra == "dev"
Requires-Dist: black<25.0,>=23.0; extra == "dev"
Requires-Dist: isort<6.0,>=5.0; extra == "dev"
Requires-Dist: mypy<2.0,>=1.0; extra == "dev"
Requires-Dist: torch<3.0,>=2.0.0; extra == "dev"
